spf/PluginMount.py
spf/__init__.py
simple_plugin_framework-0.1.0.dist-info/LICENSE
simple_plugin_framework-0.1.0.dist-info/METADATA
simple_plugin_framework-0.1.0.dist-info/WHEEL
simple_plugin_framework-0.1.0.dist-info/top_level.txt
simple_plugin_framework-0.1.0.dist-info/RECORD
