Metadata-Version: 2.1
Name: simple-plugin-framework
Version: 0.1.0
Summary: A Simple Plugin Framework
License-File: LICENSE
Provides-Extra: dev
Requires-Dist: pre-commit ; extra == 'dev'
Requires-Dist: pdoc3 ; extra == 'dev'
Requires-Dist: black ; extra == 'dev'
Requires-Dist: ipykernel ; extra == 'dev'
Requires-Dist: jupyter ; extra == 'dev'
Requires-Dist: notebook ; extra == 'dev'
Requires-Dist: mkdocs ; extra == 'dev'
Requires-Dist: mkdocstrings[python] ; extra == 'dev'
Requires-Dist: mkdocs-material ; extra == 'dev'
Requires-Dist: mkdocs-jupyter ; extra == 'dev'
Requires-Dist: ruff ; extra == 'dev'
Requires-Dist: pydocstringformatter ; extra == 'dev'
Requires-Dist: pytest ; extra == 'dev'
